{
    "web_filename": "website-design",
    "catagory": "Technology",
    "title": "Website Design ",
    "description": "An On-Brand Experience Optimized for Chinese Customers,An On-Brand Experience Optimized for Chinese Customers",
    "content_tag": [
        "\n\n\t\n\t\t\n\t\t\n\t\t\t\t\t\t\n\t\t\t\t\n\t\t\t\n\t\t\t\t\t\t\n\t\t\t\t\n\t\t\t\t\tToggle navigation\n\t\t\t\t\n\t\t\t\t\n\t\t\t\t\n\t\t\t\t\n\t\t\t\t\n\t\t\t\t\n\t\t\t\t\n\t\t\t\n\t\t\n\t\t\n\t\t\t\t\t\t\t\t\t\t\t\t\r\n\t\t\t\t\t\t\t\r\n\t\t\t\t\t\t\t\tMarketing\r\n\t\t\t\t\t\t\t\t\r\n\t\t\t\t\t\t\t\t\t\t\t\t\t\t\t\r\n\t\t\t\t\t\t\t\t\t\r\n\t\t\t\t\t\t\t\t\t\t\r\n\t\t\t\t\t\t\t\t\t\t\t\t\t\t\t\t\t\t\t\r\n\t\t\t\t\t\t\t\t\t\r\n\t\t\t\t\t\t\t\t\t\tChinese Brand Development \r\n\t\t\t\t\t\t\t\t\t\r\n\t\t\t\t\t\t\t\t\t\t\t\t\t\t\t\t\r\n\t\t\t\t\t\t\t\t\t\r\n\t\t\t\t\t\t\t\t\t\tGraphic Design Production \r\n\t\t\t\t\t\t\t\t\t\r\n\t\t\t\t\t\t\t\t\t\t\t\t\t\t\t\t\r\n\t\t\t\t\t\t\t\t\t\r\n\t\t\t\t\t\t\t\t\t\tWebsite Analytics\r\n\t\t\t\t\t\t\t\t\t\r\n\t\t\t\t\t\t\t\t\t\t\t\t\t\t\t\t\r\n\t\t\t\t\t\t\t\t\t\r\n\t\t\t\t\t\t\t\t\t\tCampaign Tracking Dashboards\r\n\t\t\t\t\t\t\t\t\t\r\n\t\t\t\t\t\t\t\t\t\t\t\t\t\t\t\t\r\n\t\t\t\t\t\t\t\t\t\r\n\t\t\t\t\t\t\t\t\t\tMarket Analysis\r\n\t\t\t\t\t\t\t\t\t\r\n\t\t\t\t\t\t\t\t\t\t\t\t\t\t\t\t\r\n\t\t\t\t\t\t\t\t\t\r\n\t\t\t\t\t\t\t\t\t\tMobile Advertising\r\n\t\t\t\t\t\t\t\t\t\r\n\t\t\t\t\t\t\t\t\t\t\t\t\t\t\t\t\r\n\t\t\t\t\t\t\t\t\t\r\n\t\t\t\t\t\t\t\t\t\tPay-Per-Click Advertising (PPC)\r\n\t\t\t\t\t\t\t\t\t\r\n\t\t\t\t\t\t\t\t\t\t\t\t\t\t\t\t\r\n\t\t\t\t\t\t\t\t\t\r\n\t\t\t\t\t\t\t\t\t\tSearch Engine Optimization (SEO)\r\n\t\t\t\t\t\t\t\t\t\r\n\t\t\t\t\t\t\t\t\t\t\t\t\t\t\t\t\r\n\t\t\t\t\t\t\t\t\t\r\n\t\t\t\t\t\t\t\t\t\teCommerce\r\n\t\t\t\t\t\t\t\t\t\r\n\t\t\t\t\t\t\t\t\t\t\t\t\t\t\t\t\r\n\t\t\t\t\t\t\t\t\t\r\n\t\t\t\t\t\t\t\t\t\tContent Localization & Translations Production\r\n\t\t\t\t\t\t\t\t\t\r\n\t\t\t\t\t\t\t\t\t\t\t\t\t\t\t\t\r\n\t\t\t\t\t\t\t\t\t\r\n\t\t\t\t\t\t\t\t\t\tDisplay Advertising\r\n\t\t\t\t\t\t\t\t\t\r\n\t\t\t\t\t\t\t\t\t\t\t\t\t\t\t\t\r\n\t\t\t\t\t\t\t\t\t\r\n\t\t\t\t\t\t\t\t\t\tContent Marketing\r\n\t\t\t\t\t\t\t\t\t\r\n\t\t\t\t\t\t\t\t\t\t\t\t\t\t\t\t\r\n\t\t\t\t\t\t\t\t\t\r\n\t\t\t\t\t\t\t\t\t\tDirect Marketing\r\n\t\t\t\t\t\t\t\t\t\r\n\t\t\t\t\t\t\t\t\t\t\t\t\t\t\t\t\r\n\t\t\t\t\t\t\t\t\t\r\n\t\t\t\t\t\t\t\t\t\tChannel Strategy\r\n\t\t\t\t\t\t\t\t\t\r\n\t\t\t\t\t\t\t\t\t\t\t\t\t\t\t\t\r\n\t\t\t\t\t\t\t\t\t\r\n\t\t\t\t\t\t\t\t\t\tCampaign Management Dashboards\r\n\t\t\t\t\t\t\t\t\t\r\n\t\t\t\t\t\t\t\t\t\t\t\t\t\t\t\t\r\n\t\t\t\t\t\t\t\t\t\r\n\t\t\t\t\t\t\t\t\t\tDigital Public Relations\r\n\t\t\t\t\t\t\t\t\t\r\n\t\t\t\t\t\t\t\t\t\t\t\t\t\t\t\t\r\n\t\t\t\t\t\t\t\t\t\r\n\t\t\t\t\t\t\t\t\t\tAsset Localization \r\n\t\t\t\t\t\t\t\t\t\r\n\t\t\t\t\t\t\t\t\t\t\t\t\t\t\t\t\r\n\t\t\t\t\t\t\t\t\t\r\n\t\t\t\t\t\t\t\t\t\tAnalytics\r\n\t\t\t\t\t\t\t\t\t\r\n\t\t\t\t\t\t\t\t\t\t\t\t\t\t\r\n\t\t\t\t\t\t\t\r\n\t\t\t\t\t\t\t\tTechnology\r\n\t\t\t\t\t\t\t\t\r\n\t\t\t\t\t\t\t\t\t\t\t\t\t\t\t\r\n\t\t\t\t\t\t\t\t\t\r\n\t\t\t\t\t\t\t\t\t\t\r\n\t\t\t\t\t\t\t\t\t\t\t\t\t\t\t\t\t\t\t\r\n\t\t\t\t\t\t\t\t\t\r\n\t\t\t\t\t\t\t\t\t\tAnalytics\r\n\t\t\t\t\t\t\t\t\t\r\n\t\t\t\t\t\t\t\t\t\t\t\t\t\t\t\t\r\n\t\t\t\t\t\t\t\t\t\r\n\t\t\t\t\t\t\t\t\t\tBusiness Integration Solutions\r\n\t\t\t\t\t\t\t\t\t\r\n\t\t\t\t\t\t\t\t\t\t\t\t\t\t\t\t\r\n\t\t\t\t\t\t\t\t\t\r\n\t\t\t\t\t\t\t\t\t\tChina Cloud Hosting\r\n\t\t\t\t\t\t\t\t\t\r\n\t\t\t\t\t\t\t\t\t\t\t\t\t\t\t\t\r\n\t\t\t\t\t\t\t\t\t\r\n\t\t\t\t\t\t\t\t\t\tContent Delivery / Distribution Network (CDN)\r\n\t\t\t\t\t\t\t\t\t\r\n\t\t\t\t\t\t\t\t\t\t\t\t\t\t\t\t\r\n\t\t\t\t\t\t\t\t\t\r\n\t\t\t\t\t\t\t\t\t\teCommerce \r\n\t\t\t\t\t\t\t\t\t\r\n\t\t\t\t\t\t\t\t\t\t\t\t\t\t\t\t\r\n\t\t\t\t\t\t\t\t\t\r\n\t\t\t\t\t\t\t\t\t\tMicrosoft Dynamics\r\n\t\t\t\t\t\t\t\t\t\r\n\t\t\t\t\t\t\t\t\t\t\t\t\t\t\t\t\r\n\t\t\t\t\t\t\t\t\t\r\n\t\t\t\t\t\t\t\t\t\tMobile Application Development\r\n\t\t\t\t\t\t\t\t\t\r\n\t\t\t\t\t\t\t\t\t\t\t\t\t\t\t\t\r\n\t\t\t\t\t\t\t\t\t\r\n\t\t\t\t\t\t\t\t\t\tMobile Application Publishing\r\n\t\t\t\t\t\t\t\t\t\r\n\t\t\t\t\t\t\t\t\t\t\t\t\t\t\t\t\r\n\t\t\t\t\t\t\t\t\t\r\n\t\t\t\t\t\t\t\t\t\tMobile Websites Design & Development\r\n\t\t\t\t\t\t\t\t\t\r\n\t\t\t\t\t\t\t\t\t\t\t\t\t\t\t\t\r\n\t\t\t\t\t\t\t\t\t\r\n\t\t\t\t\t\t\t\t\t\tPayment Gateway\r\n\t\t\t\t\t\t\t\t\t\r\n\t\t\t\t\t\t\t\t\t\t\t\t\t\t\t\t\r\n\t\t\t\t\t\t\t\t\t\r\n\t\t\t\t\t\t\t\t\t\tScraping\r\n\t\t\t\t\t\t\t\t\t\r\n\t\t\t\t\t\t\t\t\t\t\t\t\t\t\t\t\r\n\t\t\t\t\t\t\t\t\t\r\n\t\t\t\t\t\t\t\t\t\tTechnology Solutions\r\n\t\t\t\t\t\t\t\t\t\r\n\t\t\t\t\t\t\t\t\t\t\t\t\t\t\t\t\r\n\t\t\t\t\t\t\t\t\t\r\n\t\t\t\t\t\t\t\t\t\tWebsite Deployment\r\n\t\t\t\t\t\t\t\t\t\r\n\t\t\t\t\t\t\t\t\t\t\t\t\t\t\t\t\r\n\t\t\t\t\t\t\t\t\t\r\n\t\t\t\t\t\t\t\t\t\tWebsite Design\r\n\t\t\t\t\t\t\t\t\t\r\n\t\t\t\t\t\t\t\t\t\t\t\t\t\t\t\t\r\n\t\t\t\t\t\t\t\t\t\r\n\t\t\t\t\t\t\t\t\t\tChinalytics\r\n\t\t\t\t\t\t\t\t\t\r\n\t\t\t\t\t\t\t\t\t\t\t\t\t\t\r\n\t\t\t\t\t\t\t\r\n\t\t\t\t\t\t\t\tConsulting\r\n\t\t\t\t\t\t\t\t\r\n\t\t\t\t\t\t\t\t\t\t\t\t\t\t\t\r\n\t\t\t\t\t\t\t\t\t\r\n\t\t\t\t\t\t\t\t\t\t\r\n\t\t\t\t\t\t\t\t\t\t\t\t\t\t\t\t\t\t\t\r\n\t\t\t\t\t\t\t\t\t\r\n\t\t\t\t\t\t\t\t\t\tLegal & Structural Setup\r\n\t\t\t\t\t\t\t\t\t\r\n\t\t\t\t\t\t\t\t\t\t\t\t\t\t\t\t\r\n\t\t\t\t\t\t\t\t\t\r\n\t\t\t\t\t\t\t\t\t\tLicensing\r\n\t\t\t\t\t\t\t\t\t\r\n\t\t\t\t\t\t\t\t\t\t\t\t\t\t\t\t\r\n\t\t\t\t\t\t\t\t\t\r\n\t\t\t\t\t\t\t\t\t\tLogistics & Fulfillment\r\n\t\t\t\t\t\t\t\t\t\r\n\t\t\t\t\t\t\t\t\t\t\t\t\t\t\t\t\r\n\t\t\t\t\t\t\t\t\t\r\n\t\t\t\t\t\t\t\t\t\tMarket Intelligence\r\n\t\t\t\t\t\t\t\t\t\r\n\t\t\t\t\t\t\t\t\t\t\t\t\t\t\t\t\r\n\t\t\t\t\t\t\t\t\t\r\n\t\t\t\t\t\t\t\t\t\tProject Planning & Management\r\n\t\t\t\t\t\t\t\t\t\r\n\t\t\t\t\t\t\t\t\t\t\t\t\t\t\t\t\r\n\t\t\t\t\t\t\t\t\t\r\n\t\t\t\t\t\t\t\t\t\tBusiness Integration Solutions\r\n\t\t\t\t\t\t\t\t\t\r\n\t\t\t\t\t\t\t\t\t\t\t\t\t\t\t\t\r\n\t\t\t\t\t\t\t\t\t\r\n\t\t\t\t\t\t\t\t\t\tChannel Conflict Strategies\r\n\t\t\t\t\t\t\t\t\t\r\n\t\t\t\t\t\t\t\t\t\t\t\t\t\t\t\t\r\n\t\t\t\t\t\t\t\t\t\r\n\t\t\t\t\t\t\t\t\t\tICP Registration\r\n\t\t\t\t\t\t\t\t\t\r\n\t\t\t\t\t\t\t\t\t\t\t\t\t\t\t\t\r\n\t\t\t\t\t\t\t\t\t\r\n\t\t\t\t\t\t\t\t\t\tInfrastructure Auditing\r\n\t\t\t\t\t\t\t\t\t\r\n\t\t\t\t\t\t\t\t\t\t\t\t\t\t\t\t\r\n\t\t\t\t\t\t\t\t\t\r\n\t\t\t\t\t\t\t\t\t\tSystems Design\r\n\t\t\t\t\t\t\t\t\t\r\n\t\t\t\t\t\t\t\t\t\t\t\t\t\t\t\t\r\n\t\t\t\t\t\t\t\t\t\r\n\t\t\t\t\t\t\t\t\t\tRegional Planning\r\n\t\t\t\t\t\t\t\t\t\r\n\t\t\t\t\t\t\t\t\r\n\t\t\t\t\t\t\t\r\n\t\t\t\t\t\t\t\tEngage\r\n\t\t\t\t\t\t\t\r\n\t\t\t\t\t\t\t\n\t\t\n\t\n\t\n",
        "\r\n\t\t\t\t\t\t\t\t\t\r\n\t\t\t\t\t\t\t\t\t\t\r\n\t\t\t\t\t\t\t\t\t\t\t\t\t\t\t\t\t\t\t\r\n\t\t\t\t\t\t\t\t\t\r\n\t\t\t\t\t\t\t\t\t\tChinese Brand Development \r\n\t\t\t\t\t\t\t\t\t\r\n\t\t\t\t\t\t\t\t\t\t\t\t\t\t\t\t\r\n\t\t\t\t\t\t\t\t\t\r\n\t\t\t\t\t\t\t\t\t\tGraphic Design Production \r\n\t\t\t\t\t\t\t\t\t\r\n\t\t\t\t\t\t\t\t\t\t\t\t\t\t\t\t\r\n\t\t\t\t\t\t\t\t\t\r\n\t\t\t\t\t\t\t\t\t\tWebsite Analytics\r\n\t\t\t\t\t\t\t\t\t\r\n\t\t\t\t\t\t\t\t\t\t\t\t\t\t\t\t\r\n\t\t\t\t\t\t\t\t\t\r\n\t\t\t\t\t\t\t\t\t\tCampaign Tracking Dashboards\r\n\t\t\t\t\t\t\t\t\t\r\n\t\t\t\t\t\t\t\t\t\t\t\t\t\t\t\t\r\n\t\t\t\t\t\t\t\t\t\r\n\t\t\t\t\t\t\t\t\t\tMarket Analysis\r\n\t\t\t\t\t\t\t\t\t\r\n\t\t\t\t\t\t\t\t\t\t\t\t\t\t\t\t\r\n\t\t\t\t\t\t\t\t\t\r\n\t\t\t\t\t\t\t\t\t\tMobile Advertising\r\n\t\t\t\t\t\t\t\t\t\r\n\t\t\t\t\t\t\t\t\t\t\t\t\t\t\t\t\r\n\t\t\t\t\t\t\t\t\t\r\n\t\t\t\t\t\t\t\t\t\tPay-Per-Click Advertising (PPC)\r\n\t\t\t\t\t\t\t\t\t\r\n\t\t\t\t\t\t\t\t\t\t\t\t\t\t\t\t\r\n\t\t\t\t\t\t\t\t\t\r\n\t\t\t\t\t\t\t\t\t\tSearch Engine Optimization (SEO)\r\n\t\t\t\t\t\t\t\t\t\r\n\t\t\t\t\t\t\t\t\t\t\t\t\t\t\t\t\r\n\t\t\t\t\t\t\t\t\t\r\n\t\t\t\t\t\t\t\t\t\teCommerce\r\n\t\t\t\t\t\t\t\t\t\r\n\t\t\t\t\t\t\t\t\t\t\t\t\t\t\t\t\r\n\t\t\t\t\t\t\t\t\t\r\n\t\t\t\t\t\t\t\t\t\tContent Localization & Translations Production\r\n\t\t\t\t\t\t\t\t\t\r\n\t\t\t\t\t\t\t\t\t\t\t\t\t\t\t\t\r\n\t\t\t\t\t\t\t\t\t\r\n\t\t\t\t\t\t\t\t\t\tDisplay Advertising\r\n\t\t\t\t\t\t\t\t\t\r\n\t\t\t\t\t\t\t\t\t\t\t\t\t\t\t\t\r\n\t\t\t\t\t\t\t\t\t\r\n\t\t\t\t\t\t\t\t\t\tContent Marketing\r\n\t\t\t\t\t\t\t\t\t\r\n\t\t\t\t\t\t\t\t\t\t\t\t\t\t\t\t\r\n\t\t\t\t\t\t\t\t\t\r\n\t\t\t\t\t\t\t\t\t\tDirect Marketing\r\n\t\t\t\t\t\t\t\t\t\r\n\t\t\t\t\t\t\t\t\t\t\t\t\t\t\t\t\r\n\t\t\t\t\t\t\t\t\t\r\n\t\t\t\t\t\t\t\t\t\tChannel Strategy\r\n\t\t\t\t\t\t\t\t\t\r\n\t\t\t\t\t\t\t\t\t\t\t\t\t\t\t\t\r\n\t\t\t\t\t\t\t\t\t\r\n\t\t\t\t\t\t\t\t\t\tCampaign Management Dashboards\r\n\t\t\t\t\t\t\t\t\t\r\n\t\t\t\t\t\t\t\t\t\t\t\t\t\t\t\t\r\n\t\t\t\t\t\t\t\t\t\r\n\t\t\t\t\t\t\t\t\t\tDigital Public Relations\r\n\t\t\t\t\t\t\t\t\t\r\n\t\t\t\t\t\t\t\t\t\t\t\t\t\t\t\t\r\n\t\t\t\t\t\t\t\t\t\r\n\t\t\t\t\t\t\t\t\t\tAsset Localization \r\n\t\t\t\t\t\t\t\t\t\r\n\t\t\t\t\t\t\t\t\t\t\t\t\t\t\t\t\r\n\t\t\t\t\t\t\t\t\t\r\n\t\t\t\t\t\t\t\t\t\tAnalytics\r\n\t\t\t\t\t\t\t\t\t\r\n\t\t\t\t\t\t\t\t",
        "\r\n\t\t\t\t\t\t\t\t\t\r\n\t\t\t\t\t\t\t\t\t\t\r\n\t\t\t\t\t\t\t\t\t\t\t\t\t\t\t\t\t\t\t\r\n\t\t\t\t\t\t\t\t\t\r\n\t\t\t\t\t\t\t\t\t\tAnalytics\r\n\t\t\t\t\t\t\t\t\t\r\n\t\t\t\t\t\t\t\t\t\t\t\t\t\t\t\t\r\n\t\t\t\t\t\t\t\t\t\r\n\t\t\t\t\t\t\t\t\t\tBusiness Integration Solutions\r\n\t\t\t\t\t\t\t\t\t\r\n\t\t\t\t\t\t\t\t\t\t\t\t\t\t\t\t\r\n\t\t\t\t\t\t\t\t\t\r\n\t\t\t\t\t\t\t\t\t\tChina Cloud Hosting\r\n\t\t\t\t\t\t\t\t\t\r\n\t\t\t\t\t\t\t\t\t\t\t\t\t\t\t\t\r\n\t\t\t\t\t\t\t\t\t\r\n\t\t\t\t\t\t\t\t\t\tContent Delivery / Distribution Network (CDN)\r\n\t\t\t\t\t\t\t\t\t\r\n\t\t\t\t\t\t\t\t\t\t\t\t\t\t\t\t\r\n\t\t\t\t\t\t\t\t\t\r\n\t\t\t\t\t\t\t\t\t\teCommerce \r\n\t\t\t\t\t\t\t\t\t\r\n\t\t\t\t\t\t\t\t\t\t\t\t\t\t\t\t\r\n\t\t\t\t\t\t\t\t\t\r\n\t\t\t\t\t\t\t\t\t\tMicrosoft Dynamics\r\n\t\t\t\t\t\t\t\t\t\r\n\t\t\t\t\t\t\t\t\t\t\t\t\t\t\t\t\r\n\t\t\t\t\t\t\t\t\t\r\n\t\t\t\t\t\t\t\t\t\tMobile Application Development\r\n\t\t\t\t\t\t\t\t\t\r\n\t\t\t\t\t\t\t\t\t\t\t\t\t\t\t\t\r\n\t\t\t\t\t\t\t\t\t\r\n\t\t\t\t\t\t\t\t\t\tMobile Application Publishing\r\n\t\t\t\t\t\t\t\t\t\r\n\t\t\t\t\t\t\t\t\t\t\t\t\t\t\t\t\r\n\t\t\t\t\t\t\t\t\t\r\n\t\t\t\t\t\t\t\t\t\tMobile Websites Design & Development\r\n\t\t\t\t\t\t\t\t\t\r\n\t\t\t\t\t\t\t\t\t\t\t\t\t\t\t\t\r\n\t\t\t\t\t\t\t\t\t\r\n\t\t\t\t\t\t\t\t\t\tPayment Gateway\r\n\t\t\t\t\t\t\t\t\t\r\n\t\t\t\t\t\t\t\t\t\t\t\t\t\t\t\t\r\n\t\t\t\t\t\t\t\t\t\r\n\t\t\t\t\t\t\t\t\t\tScraping\r\n\t\t\t\t\t\t\t\t\t\r\n\t\t\t\t\t\t\t\t\t\t\t\t\t\t\t\t\r\n\t\t\t\t\t\t\t\t\t\r\n\t\t\t\t\t\t\t\t\t\tTechnology Solutions\r\n\t\t\t\t\t\t\t\t\t\r\n\t\t\t\t\t\t\t\t\t\t\t\t\t\t\t\t\r\n\t\t\t\t\t\t\t\t\t\r\n\t\t\t\t\t\t\t\t\t\tWebsite Deployment\r\n\t\t\t\t\t\t\t\t\t\r\n\t\t\t\t\t\t\t\t\t\t\t\t\t\t\t\t\r\n\t\t\t\t\t\t\t\t\t\r\n\t\t\t\t\t\t\t\t\t\tWebsite Design\r\n\t\t\t\t\t\t\t\t\t\r\n\t\t\t\t\t\t\t\t\t\t\t\t\t\t\t\t\r\n\t\t\t\t\t\t\t\t\t\r\n\t\t\t\t\t\t\t\t\t\tChinalytics\r\n\t\t\t\t\t\t\t\t\t\r\n\t\t\t\t\t\t\t\t",
        "\r\n\t\t\t\t\t\t\t\t\t\r\n\t\t\t\t\t\t\t\t\t\t\r\n\t\t\t\t\t\t\t\t\t\t\t\t\t\t\t\t\t\t\t\r\n\t\t\t\t\t\t\t\t\t\r\n\t\t\t\t\t\t\t\t\t\tLegal & Structural Setup\r\n\t\t\t\t\t\t\t\t\t\r\n\t\t\t\t\t\t\t\t\t\t\t\t\t\t\t\t\r\n\t\t\t\t\t\t\t\t\t\r\n\t\t\t\t\t\t\t\t\t\tLicensing\r\n\t\t\t\t\t\t\t\t\t\r\n\t\t\t\t\t\t\t\t\t\t\t\t\t\t\t\t\r\n\t\t\t\t\t\t\t\t\t\r\n\t\t\t\t\t\t\t\t\t\tLogistics & Fulfillment\r\n\t\t\t\t\t\t\t\t\t\r\n\t\t\t\t\t\t\t\t\t\t\t\t\t\t\t\t\r\n\t\t\t\t\t\t\t\t\t\r\n\t\t\t\t\t\t\t\t\t\tMarket Intelligence\r\n\t\t\t\t\t\t\t\t\t\r\n\t\t\t\t\t\t\t\t\t\t\t\t\t\t\t\t\r\n\t\t\t\t\t\t\t\t\t\r\n\t\t\t\t\t\t\t\t\t\tProject Planning & Management\r\n\t\t\t\t\t\t\t\t\t\r\n\t\t\t\t\t\t\t\t\t\t\t\t\t\t\t\t\r\n\t\t\t\t\t\t\t\t\t\r\n\t\t\t\t\t\t\t\t\t\tBusiness Integration Solutions\r\n\t\t\t\t\t\t\t\t\t\r\n\t\t\t\t\t\t\t\t\t\t\t\t\t\t\t\t\r\n\t\t\t\t\t\t\t\t\t\r\n\t\t\t\t\t\t\t\t\t\tChannel Conflict Strategies\r\n\t\t\t\t\t\t\t\t\t\r\n\t\t\t\t\t\t\t\t\t\t\t\t\t\t\t\t\r\n\t\t\t\t\t\t\t\t\t\r\n\t\t\t\t\t\t\t\t\t\tICP Registration\r\n\t\t\t\t\t\t\t\t\t\r\n\t\t\t\t\t\t\t\t\t\t\t\t\t\t\t\t\r\n\t\t\t\t\t\t\t\t\t\r\n\t\t\t\t\t\t\t\t\t\tInfrastructure Auditing\r\n\t\t\t\t\t\t\t\t\t\r\n\t\t\t\t\t\t\t\t\t\t\t\t\t\t\t\t\r\n\t\t\t\t\t\t\t\t\t\r\n\t\t\t\t\t\t\t\t\t\tSystems Design\r\n\t\t\t\t\t\t\t\t\t\r\n\t\t\t\t\t\t\t\t\t\t\t\t\t\t\t\t\r\n\t\t\t\t\t\t\t\t\t\r\n\t\t\t\t\t\t\t\t\t\tRegional Planning\r\n\t\t\t\t\t\t\t\t\t\r\n\t\t\t\t\t\t\t\t",
        "\n\t\t\n\t\t\t\n\t\t\t\tTechnology\t\t\t\n\t\t\t\n\t\t\t\t\n\t\t\t\t\t\t\t\t\t\t\n\t\t\t\t\t\tWebsite Design\t\t\t\t\t\t\n\t\t\t\t\t\tAn On-Brand Experience Optimized for Chinese Customers\n\t\t\t\t\t\n\t\t\t\t\t\t\t\t\t\t\n\t\t\t\t\t\tWebsite Design\t\t\t\t\t\t\n\t\t\t\t\t\tAn On-Brand Experience Optimized for Chinese Customers\n\t\t\t\t\t\n\t\t\t\t\t\t\t\t\t\n\t\t\t\t\n\t\t\t\n\t\t\n\t",
        "\n\t\t\n\t\t\t\t\t\n\t\t\t\n\t\t\t\t\t\t\t\t\t\n\t\t\t\t\t\t\t\n\t\t\t\t\t\t\t\tOverview \t\t\t\t\t\t\t\n\t\t\t\t\t\t\n\t\t\t\t\t\t\t\t\t\t\t\t\n\t\t\t\t\t\t\t\n\t\t\t\t\t\t\t\tProcess \t\t\t\t\t\t\t\n\t\t\t\t\t\t\n\t\t\t\t\t\t\t\t\t\t\t\t\n\t\t\t\t\t\t\t\n\t\t\t\t\t\t\t\tImpact \t\t\t\t\t\t\t\n\t\t\t\t\t\t\n\t\t\t\t\t\t\t\t\t\n\t\t\t\n\t\t\t\t\n\t\t\t\t\t\t\t\t\t\n\t\t\t\t\t\tOverview \n\t\t\t\t\t\tRest assured – the cultural pundits are wrong. Principles of good UX are universal. Everyone likes clean, dynamic, image-driven, and intuitive. Everyone appreciates transparency and authenticity from your website. So the challenge for your China site lies in adjusting not for multicultural, but rather multi-tech environment adjustments. Designing for different Internet speeds, integrating with different third party APIs – a host of complexities stand between the clear messaging of your website and your target Chinese customers. WPIC offers a multi-disciplined team, experienced in addressing all China complexities, while still delivering the hallmarks of a superior website – clean code, responsive design, full integration, and user-friendly CMS. Get in touch to view our portfolio, and explore what a WPIC-designed website can do for your brand.\t\t\t\t\t\n\t\t\t\t\t\t\t\t\t\t\n\t\t\t\t\t\tProcess \n\t\t\t\t\t\t\t\t\t\t\t\n\t\t\t\t\t\t\t\t\t\t\n\t\t\t\t\t\tImpact \n\t\t\t\t\t\tA city government’s tourism department wanted to re-design its Chinese website, to increase engagement, and facilitate provider/tourist interaction. Tactics:Requirements gathering meetingMedia asset gathering and localizationMockup process - themes adapted from best-performing tourism sites worldwideDesign team deployed on approval of themeIT team installs new Drupal 7 back-end, best for English-Mandarin implementationContent optimized for China SEO and implementedIntegration for 3rd party advertising, Chinese social media, sign-upSite cloud-hosted in China Results:A cutting-edge, parralax layout, dynamic, picture-driven design garnered positive reviews from Chinese and Western press on re-launch. All site metrics greatly improved, particularly time on site (from under half a minute to over three minutes average.) Partners able to offer deals and next steps to readers. \t\t\t\t\t\n\t\t\t\t\t\t\t\t\n\t\t\n\t\t\n\t\t\t\t\t\t\t\r\n\t\t\t\t\t\t\t\r\n\t\t\t\t\t\t\t\t\r\n\t\t\t\t\t\t\t\t\tRelated Services\r\n\t\t\t\t\t\t\t\t\r\n\t\t\t\t\t\t\t\r\n\t\t\t\t\t\t\t\r\n\t\t\t\t\t\t\t\t\t\t\t\t\t\t\t\t\r\n\t\t\t\t\t\t\t\t\r\n\t\t\t\t\t\t\t\t\t\r\n\t\t\t\t\t\t\t\t\t\t\r\n\t\t\t\t\t\t\t\t\t\t\tChina Cloud Hosting\r\n\t\t\t\t\t\t\t\t\t\t\r\n\t\t\t\t\t\t\t\t\t\t\r\n\t\t\t\t\t\t\t\t\t\t\t\r\n\t\t\t\t\t\t\t\t\t\t\r\n\t\t\t\t\t\t\t\t\t\r\n\t\t\t\t\t\t\t\t\r\n\t\t\t\t\t\t\t\t\t\t\t\t\t\t\t\t\t\t\t\r\n\t\t\t\t\t\t\t\t\r\n\t\t\t\t\t\t\t\t\t\r\n\t\t\t\t\t\t\t\t\t\t\r\n\t\t\t\t\t\t\t\t\t\t\tICP Registration\r\n\t\t\t\t\t\t\t\t\t\t\r\n\t\t\t\t\t\t\t\t\t\t\r\n\t\t\t\t\t\t\t\t\t\t\t\r\n\t\t\t\t\t\t\t\t\t\t\r\n\t\t\t\t\t\t\t\t\t\r\n\t\t\t\t\t\t\t\t\r\n\t\t\t\t\t\t\t\t\t\t\t\t\t\t\t\t\t\t\t\r\n\t\t\t\t\t\t\t\t\r\n\t\t\t\t\t\t\t\t\t\r\n\t\t\t\t\t\t\t\t\t\t\r\n\t\t\t\t\t\t\t\t\t\t\tMobile Websites Design & Development\r\n\t\t\t\t\t\t\t\t\t\t\r\n\t\t\t\t\t\t\t\t\t\t\r\n\t\t\t\t\t\t\t\t\t\t\t\r\n\t\t\t\t\t\t\t\t\t\t\r\n\t\t\t\t\t\t\t\t\t\r\n\t\t\t\t\t\t\t\t\r\n\t\t\t\t\t\t\t\t\t\t\t\t\t\t\t\t\t\t\t\r\n\t\t\t\t\t\t\t\t\r\n\t\t\t\t\t\t\t\t\t\r\n\t\t\t\t\t\t\t\t\t\t\r\n\t\t\t\t\t\t\t\t\t\t\tWebsite Deployment\r\n\t\t\t\t\t\t\t\t\t\t\r\n\t\t\t\t\t\t\t\t\t\t\r\n\t\t\t\t\t\t\t\t\t\t\t\r\n\t\t\t\t\t\t\t\t\t\t\r\n\t\t\t\t\t\t\t\t\t\r\n\t\t\t\t\t\t\t\t\r\n\t\t\t\t\t\t\t\t\t\t\t\r\n\t\t\t\t\t\t\t\r\n\t\t\t\t\t\t\t\n\t",
        "\n\t\t\n\t\t\t\n\t\t\t\t\n\t\t\t\t\t\n\t\t\t\t\t\t\n\t\t\t\t\t\t\tContact Us\n\t\t\t\t\t\t\n\t\t\t\t\t\n\t\t\t\t\t\t\t\t\t\t\n\t\t\t\t\t\t\t\t\t\t\n\t\t\t\t\t\t\n\t\t\t\t\t\t\n\t\t\t\t\t\t\tGet in Touch\t\t\t\t\t\t\n\t\t\t\t\t\t\n\t\t\t\t\t\t\tWe welcome any feedback you have.\n\t\t\t\t\t\t\n\t\t\t\t\t\t\n  Name *\n \n\n\n \n\n\n\n  Email *\n \n\n\n  Phone \n \n\n\n  Message \n \n\n\n\n\n\n\n\n\n\n\n  Leave this field blank \n \n\n\t\t\t\t\t\t\n\t\t\t\t\t\n\t\t\t\t\n\t\t\t\n\t\t\t\n\t\t\n\t"
    ]
}